snailjob/__init__.py
snailjob/args.py
snailjob/cfg.py
snailjob/ctx.py
snailjob/deco.py
snailjob/err.py
snailjob/exec.py
snailjob/log.py
snailjob/main.py
snailjob/rpc.py
snailjob/utils.py
snailjob/builtins/__init__.py
snailjob/builtins/_base.py
snailjob/builtins/_script_executor.py
snailjob/builtins/_util.py
snailjob/builtins/cmd_executor.py
snailjob/builtins/http_executor.py
snailjob/builtins/powershell_executor.py
snailjob/builtins/shell_executor.py
snailjob/grpc/__init__.py
snailjob/grpc/_rpc.py
snailjob/grpc/_server.py
snailjob/grpc/snailjob.proto
snailjob/grpc/snailjob_pb2.py
snailjob/grpc/snailjob_pb2_grpc.py
snailjob/schemas/__init__.py
snailjob/schemas/_client.py
snailjob/schemas/_common.py
snailjob/schemas/_enums.py
snailjob/schemas/_server.py
rpa_robot_python_rayel-0.0.5.dist-info/METADATA
rpa_robot_python_rayel-0.0.5.dist-info/WHEEL
rpa_robot_python_rayel-0.0.5.dist-info/licenses/LICENSE
rpa_robot_python_rayel-0.0.5.dist-info/RECORD
