Metadata-Version: 2.4
Name: rpa-robot-python-rayel
Version: 0.0.5
Summary: A distributed job execution framework
Project-URL: Homepage, https://gitee.com/opensnail/snail-job-python
Project-URL: Repository, https://gitee.com/opensnail/snail-job-python
Project-URL: Documentation, https://gitee.com/opensnail/snail-job-python
Author-email: rayel <914660773@qq.com>
License: Apache-2.0
License-File: LICENSE
Keywords: distributed,job-scheduler,retry-management,task-scheduler
Classifier: Development Status :: 4 - Beta
Classifier: Intended Audience :: Developers
Classifier: License :: OSI Approved :: Apache Software License
Classifier: Operating System :: OS Independent
Classifier: Programming Language :: Python :: 3
Classifier: Programming Language :: Python :: 3.8
Classifier: Programming Language :: Python :: 3.9
Classifier: Programming Language :: Python :: 3.10
Classifier: Programming Language :: Python :: 3.11
Classifier: Programming Language :: Python :: 3.12
Classifier: Programming Language :: Python :: 3.13
Classifier: Topic :: Software Development :: Libraries :: Python Modules
Requires-Python: >=3.8
Requires-Dist: aiohttp>=3.10.9
Requires-Dist: grpcio>=1.66.2
Requires-Dist: protobuf>=5.27.2
Requires-Dist: pydantic>=2.7.4
Requires-Dist: python-dotenv>=1.0.1
Requires-Dist: requests>=2.32.3
Provides-Extra: dev
Requires-Dist: grpcio-tools>=1.66.2; extra == 'dev'
Requires-Dist: ruff>=0.3.0; extra == 'dev'
